{
    "ur": {
        "general": [
            {
                "title": "لائیو, تیل کی قیمتوں میں دو فیصد کمی، امریکہ، ایران کشیدگی کو کم کرنے کے لیے پاکستان، قطر اور علاقائی ثالث متحرک",
                "desc": "تفصیلی مضمون پڑھنے کے لیے لنک پر کلک کریں۔",
                "image": "https://ichef.bbci.co.uk/ace/ws/240/cpsprodpb/a71a/live/0efcb340-7c3c-11f1-b976-0b9c15b0ccfc.png.webp",
                "url": "https://www.bbc.com/urdu/live/cvgjyv54g48t",
                "source": "BBC Urdu",
                "date": "تازہ ترین"
            },
            {
                "title": "موبائل فون کا استعمال ریڑھ کی ہڈی، جلد اور بینائی کو کیسے متاثر کرتا ہے؟",
                "desc": "تفصیلی مضمون پڑھنے کے لیے لنک پر کلک کریں۔",
                "image": "https://ichef.bbci.co.uk/ace/ws/240/cpsprodpb/6bb2/live/55f96210-7a08-11f1-bee8-53ce494e1abc.jpg.webp",
                "url": "https://www.bbc.com/urdu/articles/clyw821dml4o",
                "source": "BBC Urdu",
                "date": "تازہ ترین"
            },
            {
                "title": "کے ٹو ایئرویز طیارہ حادثے سے جنم لینے والے سوال اور بلیک باکس کی تلاش",
                "desc": "تفصیلی مضمون پڑھنے کے لیے لنک پر کلک کریں۔",
                "image": "https://ichef.bbci.co.uk/ace/ws/240/cpsprodpb/e5c3/live/3aa1d8f0-7bd2-11f1-b976-0b9c15b0ccfc.jpg.webp",
                "url": "https://www.bbc.com/urdu/articles/cnv9l6qmejdo",
                "source": "BBC Urdu",
                "date": "تازہ ترین"
            },
            {
                "title": "بلیو پاسپورٹ، اسلحہ لائسنس: خیبرپختونخوا میں اراکین اسمبلی کے لیے نئی مراعات کا مجوزہ قانون متنازع کیوں بنا؟",
                "desc": "تفصیلی مضمون پڑھنے کے لیے لنک پر کلک کریں۔",
                "image": "https://ichef.bbci.co.uk/ace/ws/240/cpsprodpb/8fca/live/eb7e1730-7c16-11f1-8fcc-25466dd24573.jpg.webp",
                "url": "https://www.bbc.com/urdu/articles/cx2vzp8q4l8o",
                "source": "BBC Urdu",
                "date": "تازہ ترین"
            },
            {
                "title": "’محفوظ راستے‘ کا تنازع: امریکہ اور ایران کے درمیان تازہ جھڑپوں کے بعد آبنائے ہرمز سے تیل اور گیس کی ترسیل کیسے متاثر ہوئی؟",
                "desc": "تفصیلی مضمون پڑھنے کے لیے لنک پر کلک کریں۔",
                "image": "https://ichef.bbci.co.uk/ace/ws/240/cpsprodpb/b31c/live/68edb690-7c16-11f1-b976-0b9c15b0ccfc.jpg.webp",
                "url": "https://www.bbc.com/urdu/articles/c77yg7d2g34o",
                "source": "BBC Urdu",
                "date": "تازہ ترین"
            }
        ],
        "business": [],
        "technology": [],
        "sports": []
    },
    "en": {
        "general": [],
        "business": [],
        "technology": [],
        "sports": []
    }
}